{
  "opciones": {
    "btn1": "Seguridad de red",
    "Seguridad de red": {
      "Seguridad perimetral": {
        "tema": "Seguridad perimetral",
        "data": "seguridad_red/perimetral.json"
      },
      "Seguridad de endpoints": {
        "tema": "Seguridad de endpoints",
        "data": "seguridad_red/endpoints.json"
      },
      "Seguridad de la nube": {
        "tema": "Seguridad de la nube",
        "data": "seguridad_red/nube.json"
      },
      "Seguridad de aplicaciones web": {
        "tema": "Seguridad de aplicaciones web",
        "data": "seguridad_red/appweb.json"
      },
      "Seguridad de la información": {
        "tema": "Seguridad de la información",
        "data": "seguridad_red/informacion.json"
      }
    },
    "btn2": "Seguridad de datos",
    "Seguridad de datos": {
      "datos": {
        "tema": "javascript",
        "data": "programacion/javascript.json"
      },
      "react": {
        "tema": "react",
        "data": "programacion/react.json"
      },
      "node": {
        "tema": "node",
        "data": "programacion/node.json"
      }
    },

    "btn3": "Seguridad de aplicaciones",
    "Seguridad de aplicaciones": {
      "configuracion de windows": {
        "tema": "configuracion de windows",
        "data": "inicio/windows.json"
      },
      "ubuntu": {
        "tema": "ubuntu",
        "data": "inicio/ubuntu.json"
      },
      "debian": {
        "tema": "debian",
        "data": "inicio/debian.json"
      }
    }
  }
}
